Workbook

Sheet Input
A1: TOPSOE Ammonia TEA
A2: Parameter | B2: Value | C2: Unit
A3: PLANT CAPACITY
A4: NH3 product flowrate (from Aspen stream table) | B4: 15000 | C4: kg/hr
A5: Operating hours per year | B5: 8000 | C5: hr/yr
A6: NH3 selling price escalation | B6: 2 | C6: %/yr
A7: Plant operating life | B7: 10 | C7: yrs
A8: Ramp-up factor Year 1 | B8: 0.7
A9: Ramp-up factor Year 2 | B9: 0.85
A11: CAPITAL COSTS (CAPEX)
A12: Cost Index | B12: =786.7/816 -> 0.96409314
A13: Total Capital Cost (2022) | B13: 25369700 | C13: USD
A14: Total Capital Cost (2025) | B14: =25369700*B12 -> 24458754 | C14: USD
A15: Contingency (% of TCC) | B15: 15 | C15: %
A16: Engineering & PMC (% of TCC) | B16: 10 | C16: %
A17: Land cost | B17: 200000 | C17: USD
A18: Working Capital (% of FCI) | B18: 25 | C18: %
A19: FCI spend Year 0 | B19: 0.5
A20: Salvage value (% of FCI, end of life) | B20: 10 | C20: %
A22: OPERATING COSTS (OPEX)
A23: Electricity cost | B23: 1508.955 | C23: USD/hr
A24: Cooling water cost | B24: 109.456 | C24: USD/hr
A25: Refrigerant cost | B25: 146.547 | C25: USD/hr
A26: Maintenance (% of FCI per year) | B26: 3 | C26: %
A27: Labour & supervision | B27: 5000000 | C27: USD/yr
A28: Insurance & overheads (% of FCI per year) | B28: 1 | C28: %
A29: Catalyst & chemicals | B29: 2000000 | C29: USD/yr
A30: Water & miscellaneous | B30: 500000 | C30: USD/yr
A33: REVENUE
A34: NH3 base selling price | B34: 500 | C34: USD/t
A36: FINANCIAL PARAMETERS
A37: Discount rate / WACC | B37: 15 | C37: %
A38: Corporate tax rate | B38: 30 | C38: %
A39: Depreciation rate (% of FCI per year, SLM) | B39: 9 | C39: %

Sheet Calculations
A1: Calculations
C2: Unit
A3: CAPITAL
A4: Fixed Capital Investment (FCI) | B4: =Input!B14*(1+Input!B15/100+Input!B16/100) -> 30573442 | C4: USD
A5: Working Capital Investment (WCI) | B5: =Calculations!B4*Input!B18/100 -> 7643360.5 | C5: USD
A6: Salvage value (end of life) | B6: =Calculations!B4*Input!B20/100+Input!B17 -> 3257344.2 | C6: USD
A7: Total capital Investment (TCI) | B7: =Calculations!B4+Calculations!B5+Input!B17 -> 38416803 | C7: USD
A8: Annual depreciation (SLM) | B8: =Calculations!B4*Input!B39/100 -> 2751609.8 | C8: USD/yr
A10: PRODUCTION
A11: Annual NH3 production | B11: =Input!B4*Input!B5/1000 -> 120000 | C11: t/yr
A12: Annual revenue | B12: =Calculations!B11*Input!B34 -> 60000000 | C12: USD/yr
A14: OPEX
A15: Total utilities | B15: =(Input!B23+Input!B24+Input!B25)*Input!B5 -> 14119664 | C15: USD/yr
A16: Maintenance | B16: =Calculations!B4*Input!B26/100 -> 917203.26 | C16: USD/yr
A17: Insurance & overheads | B17: =Calculations!B4*Input!B28/100 -> 305734.42 | C17: USD/yr
A18: Total OPEX | B18: =Calculations!B15+Calculations!B16+Input!B27+Calculations!B17+Input!B29+Input!B30 -> 22842602 | C18: USD/yr
A19: OPEX per tonne NH3 | B19: =IF(Calculations!B11>0,Calculations!B18/Calculations!B11,0) -> 190.35501 | C19: USD/t
A21: PROFITABILITY
A22: Taxable income | B22: =Calculations!B12-Calculations!B18-Calculations!B8 -> 34405789 | C22: USD/yr
A23: Tax | B23: =MAX(0,Calculations!B22)*Input!B38/100 -> 10321737 | C23: USD/yr
A24: Net profit | B24: =Calculations!B22-Calculations!B23 -> 24084052 | C24: USD/yr
A25: After-tax cash flow | B25: =Calculations!B24+Calculations!B8 -> 26835662 | C25: USD/yr
A26: Gross margin | B26: =IF(Calculations!B12>0,(Calculations!B12-Calculations!B18)/Calculations!B12*100,0) -> 61.928997 | C26: %

Sheet Cash Flow Model
A1: TOPSOE Ammonia - Cash Flow Model (USD)
B2: Units | C2: Year 0 | D2: Year 1 | E2: Year 2 | F2: Year 3 | G2: Year 4 | H2: Year 5 | I2: Year 6 | J2: Year 7 | K2: Year 8 | L2: Year 9 | M2: Year 10 | N2: Year 11 | O2: Year 12
A3: CAPITAL EXPENDITURE
A4: Land | B4: USD | C4: =-Input!B17 -> -200000 | D4: =0 -> 0 | E4: =0 -> 0 | F4: =0 -> 0 | G4: =0 -> 0 | H4: =0 -> 0 | I4: =0 -> 0 | J4: =0 -> 0 | K4: =0 -> 0 | ... N4: =0 -> 0 | O4: =+Input!B17 -> 200000
A5: FCI | B5: USD | C5: =- Calculations!B4*Input!B19 -> -15286721 | D5: =-Calculations!B4*(1-Input!B19) -> -15286721 | E5: =0 -> 0 | F5: =0 -> 0 | G5: =0 -> 0 | H5: =0 -> 0 | I5: =0 -> 0 | J5: =0 -> 0 | K5: =0 -> 0 | L5: =0 -> 0 | ... O5: =0 -> 0
A6: WC | B6: USD | C6: =0 -> 0 | D6: =0 -> 0 | E6: =-Calculations!B5 -> -7643360.5 | F6: =0 -> 0 | G6: =0 -> 0 | H6: =0 -> 0 | I6: =0 -> 0 | J6: =0 -> 0 | K6: =0 -> 0 | L6: =0 -> 0 | M6: =0 -> 0 | N6: =0 -> 0 | O6: =+Calculations!B5 -> 7643360.5
A7: REVENUE
A8: Annual Production | B8: MM t/yr | C8: =0 -> 0 | D8: =0 -> 0 | E8: =0 -> 0 | F8: =Calculations!B11*Input!B8/1000000 -> 0.084 | G8: =Calculations!B11*Input!B9/1000000 -> 0.102 | H8: =Calculations!B11*1/1000000 -> 0.12 | I8: =Calculations!B11*1/1000000 -> 0.12 | J8: =Calculations!B11*1/1000000 -> 0.12 | K8: =Calculations!B11*1/1000000 -> 0.12 | L8: =Calculations!B11*1/1000000 -> 0.12 | M8: =Calculations!B11*1/1000000 -> 0.12 | N8: =Calculations!B11*1/1000000 -> 0.12 | O8: =Calculations!B11*1/1000000 -> 0.12
A9: NH3 Selling Price | B9: USD/t | C9: =0 -> 0 | D9: =0 -> 0 | E9: =0 -> 0 | F9: =Input!B34 -> 500 | G9: =Input!B34*(1+Input!B6/100)^1 -> 510 | H9: =Input!B34*(1+Input!B6/100)^2 -> 520.2 | I9: =Input!B34*(1+Input!B6/100)^3 -> 530.604 | J9: =Input!B34*(1+Input!B6/100)^4 -> 541.21608 | K9: =Input!B34*(1+Input!B6/100)^5 -> 552.0404 | L9: =Input!B34*(1+Input!B6/100)^6 -> 563.08121 | M9: =Input!B34*(1+Input!B6/100)^7 -> 574.34283 | N9: =Input!B34*(1+Input!B6/100)^8 -> 585.82969 | O9: =Input!B34*(1+Input!B6/100)^9 -> 597.54628
A10: Annual Revenue | B10: USD | C10: =0 -> 0 | D10: =0 -> 0 | E10: =0 -> 0 | F10: =F8*1000000*F9 -> 42000000 | G10: =G8*1000000*G9 -> 52020000 | H10: =H8*1000000*H9 -> 62424000 | I10: =I8*1000000*I9 -> 63672480 | J10: =J8*1000000*J9 -> 64945930 | K10: =K8*1000000*K9 -> 66244848 | L10: =L8*1000000*L9 -> 67569745 | M10: =M8*1000000*M9 -> 68921140 | ... O10: =O8*1000000*O9 -> 71705554
A11: OPERATING COSTS
A12: Utilities | B12: USD | C12: =0 -> 0 | D12: =0 -> 0 | E12: =0 -> 0 | F12: =(Input!B23+Input!B24+Input!B25)*Input!B5*Input!B8 -> 9883764.8 | G12: =(Input!B23+Input!B24+Input!B25)*Input!B5*Input!B9 -> 12001714 | H12: =(Input!B23+Input!B24+Input!B25)*Input!B5*1 -> 14119664 | I12: =(Input!B23+Input!B24+Input!B25)*Input!B5*1 -> 14119664 | J12: =(Input!B23+Input!B24+Input!B25)*Input!B5*1 -> 14119664 | K12: =(Input!B23+Input!B24+Input!B25)*Input!B5*1 -> 14119664 | L12: =(Input!B23+Input!B24+Input!B25)*Input!B5*1 -> 14119664 | M12: =(Input!B23+Input!B24+Input!B25)*Input!B5*1 -> 14119664 | N12: =(Input!B23+Input!B24+Input!B25)*Input!B5*1 -> 14119664 | O12: =(Input!B23+Input!B24+Input!B25)*Input!B5*1 -> 14119664
A13: Maintenance | B13: USD | C13: =0 -> 0 | D13: =0 -> 0 | E13: =0 -> 0 | F13: =Calculations!B4*Input!B26/100*Input!B8 -> 642042.28 | G13: =Calculations!B4*Input!B26/100*Input!B9 -> 779622.77 | H13: =Calculations!B4*Input!B26/100*1 -> 917203.26 | I13: =Calculations!B4*Input!B26/100*1 -> 917203.26 | J13: =Calculations!B4*Input!B26/100*1 -> 917203.26 | K13: =Calculations!B4*Input!B26/100*1 -> 917203.26 | L13: =Calculations!B4*Input!B26/100*1 -> 917203.26 | M13: =Calculations!B4*Input!B26/100*1 -> 917203.26 | N13: =Calculations!B4*Input!B26/100*1 -> 917203.26 | O13: =Calculations!B4*Input!B26/100*1 -> 917203.26
A14: Labour & Supervision | B14: USD | C14: =0 -> 0 | D14: =0 -> 0 | E14: =0 -> 0 | F14: =Input!B27 -> 5000000 | G14: =Input!B27 -> 5000000 | H14: =Input!B27 -> 5000000 | I14: =Input!B27 -> 5000000 | J14: =Input!B27 -> 5000000 | K14: =Input!B27 -> 5000000 | L14: =Input!B27 -> 5000000 | M14: =Input!B27 -> 5000000 | N14: =Input!B27 -> 5000000 | O14: =Input!B27 -> 5000000
A15: Insurance & Overheads | B15: USD | C15: =0 -> 0 | D15: =0 -> 0 | E15: =0 -> 0 | F15: =Calculations!B4*Input!B28/100*Input!B8 -> 214014.09 | G15: =Calculations!B4*Input!B28/100*Input!B9 -> 259874.26 | H15: =Calculations!B4*Input!B28/100*1 -> 305734.42 | I15: =Calculations!B4*Input!B28/100*1 -> 305734.42 | J15: =Calculations!B4*Input!B28/100*1 -> 305734.42 | K15: =Calculations!B4*Input!B28/100*1 -> 305734.42 | L15: =Calculations!B4*Input!B28/100*1 -> 305734.42 | M15: =Calculations!B4*Input!B28/100*1 -> 305734.42 | N15: =Calculations!B4*Input!B28/100*1 -> 305734.42 | O15: =Calculations!B4*Input!B28/100*1 -> 305734.42
A16: Catalyst & Chemicals | B16: USD | C16: =0 -> 0 | D16: =0 -> 0 | E16: =0 -> 0 | F16: =Input!B29 -> 2000000 | G16: =Input!B29 -> 2000000 | H16: =Input!B29 -> 2000000 | I16: =Input!B29 -> 2000000 | J16: =Input!B29 -> 2000000 | K16: =Input!B29 -> 2000000 | L16: =Input!B29 -> 2000000 | M16: =Input!B29 -> 2000000 | N16: =Input!B29 -> 2000000 | O16: =Input!B29 -> 2000000
A17: Water & Miscellaneous | B17: USD | C17: =0 -> 0 | D17: =0 -> 0 | E17: =0 -> 0 | F17: =Input!B30 -> 500000 | G17: =Input!B30 -> 500000 | H17: =Input!B30 -> 500000 | I17: =Input!B30 -> 500000 | J17: =Input!B30 -> 500000 | K17: =Input!B30 -> 500000 | L17: =Input!B30 -> 500000 | M17: =Input!B30 -> 500000 | N17: =Input!B30 -> 500000 | O17: =Input!B30 -> 500000
A18: Total Annual Operating Cost | B18: USD | C18: =SUM(C12:C17) -> 0 | D18: =SUM(D12:D17) -> 0 | E18: =SUM(E12:E17) -> 0 | F18: =SUM(F12:F17) -> 18239821 | G18: =SUM(G12:G17) -> 20541211 | H18: =SUM(H12:H17) -> 22842602 | I18: =SUM(I12:I17) -> 22842602 | J18: =SUM(J12:J17) -> 22842602 | ... O18: =SUM(O12:O17) -> 22842602
A19: PROFITABILITY
A20: Depreciation | B20: USD | C20: =0 -> 0 | D20: =0 -> 0 | E20: =0 -> 0 | F20: =Calculations!B8 -> 2751609.8 | G20: =Calculations!B8 -> 2751609.8 | H20: =Calculations!B8 -> 2751609.8 | I20: =Calculations!B8 -> 2751609.8 | J20: =Calculations!B8 -> 2751609.8 | K20: =Calculations!B8 -> 2751609.8 | L20: =Calculations!B8 -> 2751609.8 | M20: =Calculations!B8 -> 2751609.8 | N20: =Calculations!B8 -> 2751609.8 | O20: =Calculations!B8 -> 2751609.8
A21: Taxable Income | B21: USD | C21: =0 -> 0 | D21: =0 -> 0 | E21: =0 -> 0 | F21: =F10-F18-F20 -> 21008569 | G21: =G10-G18-G20 -> 28727179 | H21: =H10-H18-H20 -> 36829789 | I21: =I10-I18-I20 -> 38078269 | J21: =J10-J18-J20 -> 39351718 | K21: =K10-K18-K20 -> 40650637 | L21: =L10-L18-L20 -> 41975534 | M21: =M10-M18-M20 -> 43326929 | ... O21: =O10-O18-O20 -> 46111343
A22: Tax (30%) | B22: USD | C22: =0 -> 0 | D22: =0 -> 0 | E22: =0 -> 0 | F22: =MAX(0,F21)*Input!B38/100 -> 6302570.7 | G22: =MAX(0,G21)*Input!B38/100 -> 8618153.6 | H22: =MAX(0,H21)*Input!B38/100 -> 11048937 | I22: =MAX(0,I21)*Input!B38/100 -> 11423481 | J22: =MAX(0,J21)*Input!B38/100 -> 11805515 | K22: =MAX(0,K21)*Input!B38/100 -> 12195191 | L22: =MAX(0,L21)*Input!B38/100 -> 12592660 | M22: =MAX(0,M21)*Input!B38/100 -> 12998079 | N22: =MAX(0,N21)*Input!B38/100 -> 13411605 | O22: =MAX(0,O21)*Input!B38/100 -> 13833403
A23: Net Profit | B23: USD | C23: =0 -> 0 | D23: =0 -> 0 | E23: =0 -> 0 | F23: =F21-F22 -> 14705998 | G23: =G21-G22 -> 20109025 | H23: =H21-H22 -> 25780852 | I23: =I21-I22 -> 26654788 | J23: =J21-J22 -> 27546203 | K23: =K21-K22 -> 28455446 | L23: =L21-L22 -> 29382874 | M23: =M21-M22 -> 30328850 | ... O23: =O21-O22 -> 32277940
A24: Salvage Value (Year 12) | B24: USD | C24: =0 -> 0 | D24: =0 -> 0 | E24: =0 -> 0 | F24: =0 -> 0 | G24: =0 -> 0 | H24: =0 -> 0 | I24: =0 -> 0 | J24: =0 -> 0 | ... N24: =0 -> 0 | O24: =Calculations!B6 -> 3257344.2
A25: Annual After-Tax Cash Flow | B25: USD | C25: =C4+C5+C6 -> -15486721 | D25: =D4+D5+D6 -> -15286721 | E25: =E4+E5+E6 -> -7643360.5 | F25: =F23+F20+F24+F6+F4 -> 17457608 | G25: =G23+G20+G24+G6+G4 -> 22860635 | H25: =H23+H20+H24+H6+H4 -> 28532462 | I25: =I23+I20+I24+I6+I4 -> 29406398 | J25: =J23+J20+J24+J6+J4 -> 30297812 | K25: =K23+K20+K24+K6+K4 -> 31207055 | L25: =L23+L20+L24+L6+L4 -> 32134483 | M25: =M23+M20+M24+M6+M4 -> 33080460 | ... O25: =O23+O20+O24+O6+O4 -> 46130254
A26: Annual Cash Flow | B26: MM USD | C26: =C25/10^6 -> -15.486721 | D26: =D25/10^6 -> -15.286721 | E26: =E25/10^6 -> -7.6433605 | F26: =F25/10^6 -> 17.457608 | G26: =G25/10^6 -> 22.860635 | H26: =H25/10^6 -> 28.532462 | I26: =I25/10^6 -> 29.406398 | J26: =J25/10^6 -> 30.297812 | ... O26: =O25/10^6 -> 46.130254
A27: Discount Factor | C27: =1/(1+Input!B37/100)^0 -> 1 | D27: =1/(1+Input!B37/100)^1 -> 0.86956522 | E27: =1/(1+Input!B37/100)^2 -> 0.75614367 | F27: =1/(1+Input!B37/100)^3 -> 0.65751623 | G27: =1/(1+Input!B37/100)^4 -> 0.57175325 | H27: =1/(1+Input!B37/100)^5 -> 0.49717674 | I27: =1/(1+Input!B37/100)^6 -> 0.4323276 | J27: =1/(1+Input!B37/100)^7 -> 0.37593704 | K27: =1/(1+Input!B37/100)^8 -> 0.32690177 | L27: =1/(1+Input!B37/100)^9 -> 0.28426241 | M27: =1/(1+Input!B37/100)^10 -> 0.24718471 | N27: =1/(1+Input!B37/100)^11 -> 0.21494322 | O27: =1/(1+Input!B37/100)^12 -> 0.18690715
A28: Annual Discounted Cash Flow | B28: USD | C28: =C25*C27 -> -15486721 | D28: =D25*D27 -> -13292801 | E28: =E25*E27 -> -5779478.7 | F28: =F25*F27 -> 11478661 | G28: =G25*G27 -> 13070642 | H28: =H25*H27 -> 14185676 | I28: =I25*I27 -> 12713197 | J28: =J25*J27 -> 11390070 | ... O28: =O25*O27 -> 8622074.4
A29: Annual Discounted Cash Flow | B29: MM USD | C29: =C28/10^6 -> -15.486721 | D29: =D28/10^6 -> -13.292801 | E29: =E28/10^6 -> -5.7794787 | F29: =F28/10^6 -> 11.478661 | G29: =G28/10^6 -> 13.070642 | H29: =H28/10^6 -> 14.185676 | I29: =I28/10^6 -> 12.713197 | J29: =J28/10^6 -> 11.39007 | ... O29: =O28/10^6 -> 8.6220744
A30: Cumulative Discounted Cash Flow | B30: USD | C30: =C28 -> -15486721 | D30: =C30+D28 -> -28779522 | E30: =D30+E28 -> -34559001 | F30: =E30+F28 -> -23080340 | G30: =F30+G28 -> -10009698 | H30: =G30+H28 -> 4175978.5 | I30: =H30+I28 -> 16889176 | J30: =I30+J28 -> 28279246 | K30: =J30+K28 -> 38480888 | ... O30: =N30+O28 -> 71732390
A32: NPV | C32: =O30/10^6 -> 71.73239 | D32: MM USD
A33: IRR | C33: =IRR(C25:O25,0.15) -> 0.40511667
A34: DPBP (Year) | C34: {=IFERROR(MATCH(TRUE,C30:O30>=0,0)-1,"Not recovered")} -> 5 | D34: yr
A35: ROI | C35: =AVERAGE(C23:O23)/Calculations!B7 -> 0.5336922

Sheet EC Summary
A1: Equipment Cost Summary
A2: Equipment | B2: Equip. Cost (USD) | C2: Installed Cost (USD) | D2: Equip. Wt (lb) | E2: Installed Wt (lb) | F2: Utility Cost (USD/hr)
A3: WHB | B3: 213700 | C3: 390700 | D3: 7900 | E3: 26415 | F3: 1.156
A4: COOLER | B4: 57300 | C4: 333000 | D4: 9000 | E4: 31234 | F4: 30.489
A5: KO-DRUM | B5: 173300 | C5: 347500 | D5: 31000 | E5: 60260 | F5: 78.968
A6: CO2-PRE | B6: 57900 | C6: 190600 | D6: 13500 | E6: 26653 | F6: 0
A7: METH-PH | B7: 241300 | C7: 473000 | D7: 45000 | E7: 89761 | F7: 0
A8: 2R | B8: 585400 | C8: 880000 | D8: 94300 | E8: 129952 | F8: 0
A9: LTSC | B9: 707500 | C9: 1025200 | D9: 130600 | E9: 170471 | F9: 0
A10: BED1 | B10: 744300 | C10: 1019000 | D10: 167800 | E10: 192135 | F10: 0
A11: MLTCOMP | B11: 6523900 | C11: 7200900 | D11: 145500 | E11: 241390 | F11: 1444.794
A12: BED-PH | B12: 1148100 | C12: 1925600 | D12: 235700 | E12: 362699 | F12: 0
A13: FLASH | B13: 230700 | C13: 478700 | D13: 67800 | E13: 98552 | F13: 0
A14: LOOP-MIX | B14: 8000 | C14: 124300 | D14: 70 | E14: 5167 | F14: 0
... A26: ABS | B26: 403800 | C26: 732900 | D26: 108900 | E26: 145331 | F26: 0
A27: TOTAL | B27: =SUM(B3:B26) -> 16374500 | C27: =SUM(C3:C26) -> 24447000 | F27: =SUM(F3:F26) -> 1702.821

Sheet KPI Summary
A1: TOPSOE Ammonia TEA - Key Performance Indicators
A2: KPI | B2: Value | C2: Unit
A3: PLANT
A4: Annual NH3 Production | B4: =Calculations!B11 -> 120000 | C4: t/yr
A5: NH3 Flowrate (Aspen input) | B5: =Input!B4 -> 15000 | C5: kg/hr
A6: Operating Hours | B6: =Input!B5 -> 8000 | C6: hr/yr
A7: CAPITAL
A8: Aspen ICARUS Total Capital Cost | B8: =Input!B14 -> 24458754 | C8: USD
A9: Fixed Capital Investment (FCI) | B9: =Calculations!B4 -> 30573442 | C9: USD
A10: Working Capital (WCI) | B10: =Calculations!B5 -> 7643360.5 | C10: USD
A11: Land | B11: =Input!B17 -> 200000 | C11: USD
A12: Total Capital Outlay | B12: =Calculations!B7 -> 38416803 | C12: USD
A13: Capital Intensity (USD per t/yr) | B13: =IF(Calculations!B11>0,Calculations!B7/Calculations!B11,0) -> 320.14002 | C13: USD/(t/yr)
A14: Salvage Value | B14: =Calculations!B6 -> 3257344.2 | C14: USD
A15: OPEX
A16: Total OPEX (full capacity) | B16: =Calculations!B18 -> 22842602 | C16: USD/yr
A17: OPEX per tonne NH3 | B17: =Calculations!B19 -> 190.35501 | C17: USD/t
A18: Annual Utilities Cost | B18: =Calculations!B15 -> 14119664 | C18: USD/yr
A19: REVENUE
A20: NH3 Base Selling Price | B20: =Input!B34 -> 500 | C20: USD/t
A21: Annual Revenue (full capacity) | B21: =Calculations!B12 -> 60000000 | C21: USD/yr
A22: Gross Margin (%) | B22: =Calculations!B26 -> 61.928997 | C22: %
A23: FINANCIAL RESULTS
A24: Net Profit (full cap, after tax) | B24: =Calculations!B24 -> 24084052 | C24: USD/yr
A25: IRR | B25: ='Cash Flow Model'!C33 -> 0.40511667
A26: NPV (@ WACC) | B26: ='Cash Flow Model'!C32 -> 71.73239 | C26: USD
A27: DPBP | B27: ='Cash Flow Model'!C34 -> 5 | C27: Year
A28: WACC | B28: =Input!B37/100 -> 0.15
A29: Tax Rate | B29: =Input!B38/100 -> 0.3

Sheet OPEX Breakdown
A1: OPEX Breakdown (Full Capacity)
A2: Cost Item | B2: USD/yr | C2: USD/t NH3 | D2: % of Total
A3: Electricity | B3: =Input!B23*Input!B5 -> 12071640 | C3: =IF(Calculations!B11>0,B3/Calculations!B11,0) -> 100.597 | D3: =IF(B11>0,B3/B11*100,0) -> 52.847045
A4: Cooling Water | B4: =Input!B24*Input!B5 -> 875648 | C4: =IF(Calculations!B11>0,B4/Calculations!B11,0) -> 7.2970667 | D4: =IF(B11>0,B4/B11*100,0) -> 3.8333987
A5: Refrigerant (NH3 chiller) | B5: =Input!B25*Input!B5 -> 1172376 | C5: =IF(Calculations!B11>0,B5/Calculations!B11,0) -> 9.7698 | D5: =IF(B11>0,B5/B11*100,0) -> 5.1324101
A6: Maintenance (3% FCI/yr) | B6: =Calculations!B4*Input!B26/100 -> 917203.26 | C6: =IF(Calculations!B11>0,B6/Calculations!B11,0) -> 7.6433605 | D6: =IF(B11>0,B6/B11*100,0) -> 4.0153187
A7: Labour & Supervision | B7: =Input!B27 -> 5000000 | C7: =IF(Calculations!B11>0,B7/Calculations!B11,0) -> 41.666667 | D7: =IF(B11>0,B7/B11*100,0) -> 21.888925
A8: Insurance & Overheads (1% FCI) | B8: =Calculations!B4*Input!B28/100 -> 305734.42 | C8: =IF(Calculations!B11>0,B8/Calculations!B11,0) -> 2.5477868 | D8: =IF(B11>0,B8/B11*100,0) -> 1.3384396
A9: Catalyst & Chemicals | B9: =Input!B29 -> 2000000 | C9: =IF(Calculations!B11>0,B9/Calculations!B11,0) -> 16.666667 | D9: =IF(B11>0,B9/B11*100,0) -> 8.7555701
A10: Water & Miscellaneous | B10: =Input!B30 -> 500000 | C10: =IF(Calculations!B11>0,B10/Calculations!B11,0) -> 4.1666667 | D10: =IF(B11>0,B10/B11*100,0) -> 2.1888925
A11: TOTAL OPEX | B11: =SUM(B3:B10) -> 22842602 | C11: =IF(Calculations!B11>0,B11/Calculations!B11,0) -> 190.35501 | D11: =SUM(D3:D10) -> 100
